examples/__init__.py
examples/blueprint_example.py
examples/change_configuration.py
examples/decorator_with_combination.py
examples/quickstart.py
pf_flask_swagger/__init__.py
pf_flask_swagger/common/__init__.py
pf_flask_swagger/common/pf_flask_swagger_config.py
pf_flask_swagger/flask/__init__.py
pf_flask_swagger/flask/pf_flask_action_to_definition.py
pf_flask_swagger/flask/pf_flask_swagger.py
pf_flask_swagger/flask/pf-swagger-static/css/swagger-ui.css
pf_flask_swagger/flask/pf-swagger-static/js/swagger-ui-bundle.js
pf_flask_swagger/flask/pf-swagger-static/js/swagger-ui-standalone-preset.js
pf_flask_swagger/flask/templates/pf-swagger-ui.html
pf_flask_swagger/swagger/__init__.py
pf_flask_swagger/swagger/pf_swagger_decorator.py
pf_flask_swagger/swagger/pf_swagger_generator.py
pf_flask_swagger/swagger/pf_swagger_schema.py
pf_flask_swagger/swagger/data/__init__.py
pf_flask_swagger/swagger/data/swagger_constant.py
pf_flask_swagger/swagger/data/swagger_param_def.py
PF_Flask_Swagger-1.0.2.dist-info/LICENSE
PF_Flask_Swagger-1.0.2.dist-info/METADATA
PF_Flask_Swagger-1.0.2.dist-info/WHEEL
PF_Flask_Swagger-1.0.2.dist-info/top_level.txt
PF_Flask_Swagger-1.0.2.dist-info/RECORD
