Metadata-Version: 2.1
Name: PF-Flask-Swagger
Version: 1.0.2
Summary: Flask Swagger Documentation by Problem Fighter Library
Home-page: https://github.com/problemfighter/pf-flask-swagger
Author: Problem Fighter
Author-email: problemfighter.com@gmail.com
License: Apache 2.0
Platform: any
Classifier: Environment :: Web Environment
Classifier: Intended Audience :: Developers
Classifier: License :: OSI Approved :: Apache Software License
Classifier: Operating System :: OS Independent
Classifier: Programming Language :: Python
Classifier: Topic :: Internet :: WWW/HTTP :: Dynamic Content
Classifier: Topic :: Software Development :: Libraries :: Python Modules
Requires-Dist: Flask
Requires-Dist: Marshmallow
Requires-Dist: Apispec
Requires-Dist: PF-Flask-Rest-Com
